woopy/__init__.py
woopy-1.0.3.dist-info/LICENSE
woopy-1.0.3.dist-info/METADATA
woopy-1.0.3.dist-info/WHEEL
woopy-1.0.3.dist-info/top_level.txt
woopy-1.0.3.dist-info/RECORD
