Metadata-Version: 2.1
Name: woopy
Version: 1.0.3
Summary: A minimal Python API for WooTrade
Home-page: https://github.com/kasperdokter/woopy
Author: Kasper Dokter
Author-email: k.p.c.dokter@gmail.com
License: UNKNOWN
Project-URL: Bug Tracker, https://github.com/kasperdokter/woopy/issues
Platform: UNKNOWN
Classifier: Programming Language :: Python :: 3
Classifier: License :: OSI Approved :: MIT License
Classifier: Operating System :: OS Independent
Requires-Python: >=3.6
License-File: LICENSE
Requires-Dist: requests
Requires-Dist: websockets
